{
  "description": "Töltsd ki az üres helyeket a „to have” ige helyes alakjával! (have / has / don't have / doesn't have)",
  "items": [
    
    { "sentence": "I ______ a big dog.", "answer": "have", "hint": "(+)" },
    { "sentence": "She ______ blue eyes", "answer": "has", "hint": "(+)" },
    { "sentence": "We ______ a meeting today", "answer": "have", "hint": "(+)" },
    { "sentence": "He ______ a car. He walks to work.", "answer": "doesn't have", "hint": "(-)" },
    { "sentence": "They ______ a lot of time", "answer": "have", "hint": "(+)" },
    { "sentence": "You ______ a nice phone.", "answer": "have", "hint": "(+)" },
    { "sentence": "The laptop is old. It ______ a good battery.", "answer": "doesn't have", "hint": "(-)" },
    { "sentence": "Peter ______ a job. He is happy.", "answer": "has", "hint": "(+)" },
    { "sentence": "I am poor. I ______ money.", "answer": "don't have", "hint": "(-)" },
    { "sentence": "She ______ a sister. She is an only child.", "answer": "doesn't have", "hint": "(-)" },
    { "sentence": "Mark and David ______ a meeting now.", "answer": "have", "hint": "(+)" },
    { "sentence": "This office ______ a big screen.", "answer": "has", "hint": "(+)" },
    { "sentence": "You look busy. Do you ______ time for a coffee?", "answer": "have", "hint": "(+)" },
    { "sentence": "We ______ a problem with the computer.", "answer": "have", "hint": "(+)" },
    { "sentence": "He ______ a pen. Can you give him one?", "answer": "doesn't have", "hint": "(-)" },
    { "sentence": "They are rich. They ______ a beautiful house.", "answer": "have", "hint": "(+)" },
    { "sentence": "My phone is dead. It ______ a good battery.", "answer": "doesn't have", "hint": "(-)" },
    { "sentence": "I ______ a key to this office. Can you open it?", "answer": "don't have", "hint": "(-)" },
    { "sentence": "She ______ a very nice manager.", "answer": "has", "hint": "(+)" },
    { "sentence": "The house ______ four rooms.", "answer": "has", "hint": "(+)" },
    { "sentence": "We are hungry but we ______ food.", "answer": "don't have", "hint": "(-)" },
    { "sentence": "I ______ a question about the project.", "answer": "have", "hint": "(+)" },
    { "sentence": "He ______ a new laptop for work.", "answer": "has", "hint": "(+)" },
    { "sentence": "Mary is lonely. She ______ any friends here.", "answer": "doesn't have", "hint": "(-)" },
    { "sentence": "They ______ a big dog in their garden.", "answer": "have", "hint": "(+)" },
    { "sentence": "You ______ a beautiful smile.", "answer": "have", "hint": "(+)" },
    { "sentence": "The car is empty. It ______ petrol.", "answer": "doesn't have", "hint": "(-)" },
    { "sentence": "We ______ a holiday in July.", "answer": "have", "hint": "(+)" },
    { "sentence": "He ______ a brother and a sister.", "answer": "has", "hint": "(+)" },
    { "sentence": "I ______ a laptop. I only use a telephone.", "answer": "don't have", "hint": "(-)" },
    { "sentence": "The students ______ a test today.", "answer": "have", "hint": "(+)" },
    { "sentence": "She ______ a key to the front door.", "answer": "has", "hint": "(+)" },
    { "sentence": "I am sorry, I ______ the answer to your question.", "answer": "don't have", "hint": "(-)" },
    { "sentence": "This book ______ many interesting pages.", "answer": "has", "hint": "(+)" },
    { "sentence": "You ______ a nice car. Is it new?", "answer": "have", "hint": "(+)" },
    { "sentence": "He ______ a job in a bank.", "answer": "has", "hint": "(+)" },
    { "sentence": "They ______ a meeting at 10 o'clock.", "answer": "don't have", "hint": "(-)" },
    { "sentence": "This apartment ______ a big kitchen.", "answer": "has", "hint": "(+)" },
    { "sentence": "We ______ a clean office.", "answer": "have", "hint": "(+)" },
    { "sentence": "She ______ a black pen in her bag.", "answer": "doesn't have", "hint": "(-)" },
    { "sentence": "I ______ a problem with my telephone screen.", "answer": "have", "hint": "(+)" },
    { "sentence": "You ______ a meeting with the boss today.", "answer": "have", "hint": "(+)" },
    { "sentence": "The dog ______ blue eyes. It is beautiful.", "answer": "has", "hint": "(+)" },
    { "sentence": "He ______ any money in his pocket.", "answer": "doesn't have", "hint": "(-)" },
    { "sentence": "They ______ a big family.", "answer": "have", "hint": "(+)" },
    { "sentence": "We ______ a physical key for this office. We use a card.", "answer": "don't have", "hint": "(-)" },
    { "sentence": "I ______ a nice house in Budapest.", "answer": "have", "hint": "(+)" },
    { "sentence": "The manager ______ time to talk to you right now.", "answer": "doesn't have", "hint": "(-)" },
    { "sentence": "She ______ a happy life.", "answer": "has", "hint": "(+)" },
    { "sentence": "You ______ a problem. I can help you.", "answer": "have", "hint": "(+)" }
  ]
}